otumat/__init__.py
otumat/command_line.py
otumat/usage.py
otumat/version.py
otumat/watch.py
otumat-0.3.1.dist-info/LICENSE
otumat-0.3.1.dist-info/METADATA
otumat-0.3.1.dist-info/WHEEL
otumat-0.3.1.dist-info/entry_points.txt
otumat-0.3.1.dist-info/top_level.txt
otumat-0.3.1.dist-info/RECORD
