Metadata-Version: 2.1
Name: otumat
Version: 0.3.1
Summary: A suite of maintainer tools and utilities for pip packages.
Home-page: https://github.com/datajoint/otumat
Author: Raphael Guzman
Author-email: raphael.h.guzman@gmail.com
License: UNKNOWN
Platform: UNKNOWN
Classifier: Programming Language :: Python :: 3
Classifier: License :: OSI Approved :: MIT License
Classifier: Operating System :: OS Independent
Requires-Dist: cryptography
Requires-Dist: flask
Requires-Dist: appdirs
Requires-Dist: watchdog
